calvera/__init__.py
calvera/bandits/__init__.py
calvera/bandits/abstract_bandit.py
calvera/bandits/linear_bandit.py
calvera/bandits/linear_ts_bandit.py
calvera/bandits/linear_ucb_bandit.py
calvera/bandits/neural_bandit.py
calvera/bandits/neural_linear_bandit.py
calvera/bandits/neural_ts_bandit.py
calvera/bandits/neural_ucb_bandit.py
calvera/benchmark/__init__.py
calvera/benchmark/analyzer.py
calvera/benchmark/benchmark.py
calvera/benchmark/environment.py
calvera/benchmark/logger_decorator.py
calvera/benchmark/network_wrappers.py
calvera/benchmark/datasets/__init__.py
calvera/benchmark/datasets/abstract_dataset.py
calvera/benchmark/datasets/covertype.py
calvera/benchmark/datasets/imdb_reviews.py
calvera/benchmark/datasets/mnist.py
calvera/benchmark/datasets/movie_lens.py
calvera/benchmark/datasets/statlog.py
calvera/benchmark/datasets/synthetic.py
calvera/benchmark/datasets/synthetic_combinatorial.py
calvera/benchmark/datasets/tiny_imagenet.py
calvera/benchmark/datasets/wheel.py
calvera/utils/__init__.py
calvera/utils/action_input_type.py
calvera/utils/data_sampler.py
calvera/utils/data_storage.py
calvera/utils/multiclass.py
calvera/utils/selectors.py
calvera-1.0.2.dist-info/LICENSE
calvera-1.0.2.dist-info/METADATA
calvera-1.0.2.dist-info/WHEEL
calvera-1.0.2.dist-info/top_level.txt
calvera-1.0.2.dist-info/RECORD
