Metadata-Version: 2.2
Name: calvera
Version: 1.0.2
Summary: Package that will offer a small collection of different (Neural) Bandit algorithms with different feedback strategies.
Author-email: Parisa Shahabinejad <parisa.shahabinejad@student.hpi.de>, Philipp Kolbe <philipp.kolbe@student.hpi.de>, Robert Weeke <robert.weeke@student.hpi.de>
License: MIT
Project-URL: Homepage, https://github.com/neural-bandits/calvera
Project-URL: Issues, https://github.com/neural-bandits/calvera/issues
Project-URL: Documentation, https://neural-bandits.github.io/calvera/
Project-URL: Repository, https://github.com/neural-bandits/calvera
Keywords: python,bandits,neural networks,machine learning
Classifier: Programming Language :: Python :: 3
Classifier: Programming Language :: Python :: 3.10
Classifier: License :: OSI Approved :: MIT License
Classifier: Operating System :: OS Independent
Classifier: Development Status :: 4 - Beta
Requires-Python: >=3.10
License-File: LICENSE
Requires-Dist: lightning
Requires-Dist: torch
Requires-Dist: torchvision
Requires-Dist: torchaudio
Provides-Extra: dev
Requires-Dist: black; extra == "dev"
Requires-Dist: black[jupyter]; extra == "dev"
Requires-Dist: ruff; extra == "dev"
Requires-Dist: isort; extra == "dev"
Requires-Dist: mypy; extra == "dev"
Requires-Dist: pytest; extra == "dev"
Requires-Dist: pytest-cov; extra == "dev"
Requires-Dist: mkdocs; extra == "dev"
Requires-Dist: mkdocs-material; extra == "dev"
Requires-Dist: mkdocstrings; extra == "dev"
Requires-Dist: mkdocstrings[python]; extra == "dev"
Requires-Dist: build; extra == "dev"
Requires-Dist: twine; extra == "dev"
Provides-Extra: benchmark
Requires-Dist: numpy; extra == "benchmark"
Requires-Dist: matplotlib; extra == "benchmark"
Requires-Dist: pandas; extra == "benchmark"
Requires-Dist: ucimlrepo; extra == "benchmark"
Requires-Dist: timm; extra == "benchmark"
Requires-Dist: transformers; extra == "benchmark"
Requires-Dist: scikit-learn; extra == "benchmark"
